{
  "project_info": {
    "project_number": "67746917873",
    "project_id": "women-project-2024",
    "storage_bucket": "women-project-2024.firebasestorage.app"
  },
  "client": [
    {
      "client_info": {
        "mobilesdk_app_id": "1:67746917873:android:bf70f991795986c74da850",
        "android_client_info": {
          "package_name": "iq.gov.ur.eyn.womenvision"
        }
      },
      "oauth_client": [],
      "api_key": [
        {
          "current_key": "AIzaSyAmwS9_h1U4BYJUHtY3WJU3SqnIlZhxOrk"
        }
      ],
      "services": {
        "appinvite_service": {
          "other_platform_oauth_client": []
        }
      }
    }
  ],
  "configuration_version": "1"
}